generalbrowser/__init__.py
generalbrowser/assets/__init__.py
generalbrowser/assets/account/__init__.py
generalbrowser/assets/account/client.py
generalbrowser/assets/account/clientmodel.py
generalbrowser/assets/account/clientpage.py
generalbrowser/assets/account/model.py
generalbrowser/assets/account/server.py
generalbrowser/assets/base/__init__.py
generalbrowser/assets/base/client.py
generalbrowser/assets/base/client_and_server.py
generalbrowser/assets/base/clientmodel.py
generalbrowser/assets/base/clientpage.py
generalbrowser/assets/base/model.py
generalbrowser/assets/base/server.py
generalbrowser/test/test_generalbrowser.py
generalbrowser-0.0.9.dist-info/LICENSE
generalbrowser-0.0.9.dist-info/METADATA
generalbrowser-0.0.9.dist-info/WHEEL
generalbrowser-0.0.9.dist-info/top_level.txt
generalbrowser-0.0.9.dist-info/RECORD
