Metadata-Version: 2.1
Name: generalbrowser
Version: 0.0.9
Summary: Missing description.
Home-page: https://github.com/ManderaGeneral/generalbrowser
Author: Rickard "Mandera" Abraham
Author-email: rickard.abraham@gmail.com
License: mit
Platform: UNKNOWN
Classifier: Programming Language :: Python :: 3.8
Classifier: Programming Language :: Python :: 3.9
Classifier: License :: OSI Approved :: MIT License
Classifier: Operating System :: Microsoft :: Windows
Classifier: Operating System :: POSIX :: Linux
Requires-Python: >=3.8, <3.10
Requires-Dist: generallibrary
Requires-Dist: generalfile
Requires-Dist: generalgui
Requires-Dist: django
Requires-Dist: djangorestframework
Requires-Dist: dill
Requires-Dist: requests
